pyplelogger/__init__.py
pyplelogger/pyplelogger.py
pyplelogger-0.1.8.dist-info/LICENSE
pyplelogger-0.1.8.dist-info/METADATA
pyplelogger-0.1.8.dist-info/WHEEL
pyplelogger-0.1.8.dist-info/top_level.txt
pyplelogger-0.1.8.dist-info/RECORD
