Metadata-Version: 2.1
Name: pyplelogger
Version: 0.1.8
Summary: Simple logger in python mainly used for CLI tool like argparse
Home-page: UNKNOWN
Author: KeisukeYamashita
Author-email: 19yamashita15@gmail.com
License: MIT
Keywords: logger cli logging
Platform: UNKNOWN
Classifier: Programming Language :: Python :: 3.6
Classifier: License :: OSI Approved :: MIT License
